skspark/__init__.py
skspark/model_selection.py
skspark/spark_base_search_cv.py
skspark/sklearn_0_19/__init__.py
skspark/sklearn_0_19/model_selection.py
skspark/sklearn_0_19/spark_base_search_cv.py
skspark/sklearn_0_20/__init__.py
skspark/sklearn_0_20/_search.py
skspark/sklearn_0_21/__init__.py
skspark/sklearn_0_21/_search.py
skspark/sklearn_0_22/__init__.py
skspark/sklearn_0_22/_search.py
test/__init__.py
test/pyspark_test.py
test/resource_warning_tests.py
test/sklearn_version_specific_utils.py
test/test_direct_comparison.py
test/test_misc.py
test/test_model_selection.py
test/test_parameterised_tests.py
test/test_specific_regression_tests.py
tests/__init__.py
tests/pyspark_test.py
tests/resource_warning_tests.py
tests/test_direct_comparison.py
tests/test_misc.py
tests/test_model_selection.py
tests/test_specific_regression_tests.py
scikit_spark-0.4.0.dist-info/LICENSE
scikit_spark-0.4.0.dist-info/METADATA
scikit_spark-0.4.0.dist-info/WHEEL
scikit_spark-0.4.0.dist-info/top_level.txt
scikit_spark-0.4.0.dist-info/RECORD
