Metadata-Version: 2.1
Name: scikit-spark
Version: 0.4.0
Summary: Spark acceleration for Scikit-Learn cross validation techniques
Home-page: https://github.com/scikit-spark/scikit-spark
Author: Ganesh N. Sivalingam
Author-email: g.n.sivalingam@gmail.com
License: Apache 2.0
Keywords: spark,pyspark,scikit-learn,sklearn,machine learning,random search,grid search
Platform: UNKNOWN
Requires-Dist: numpy (>=1.13.0)
Requires-Dist: six (==1.11.0)
